config_keeper/__init__.py
config_keeper/__main__.py
config_keeper/__settings.py
config_keeper/commands/__init__.py
config_keeper/commands/common/__init__.py
config_keeper/commands/common/autocompletion.py
config_keeper/commands/common/helps.py
config_keeper/commands/common/sync.py
config_keeper/commands/config.py
config_keeper/commands/paths.py
config_keeper/commands/project.py
config_keeper/config.py
config_keeper/exceptions.py
config_keeper/lazy_settings.py
config_keeper/output.py
config_keeper/progress.py
config_keeper/sync_handler.py
config_keeper/validation.py
config_keeper2-1.1.2.dist-info/LICENSE
config_keeper2-1.1.2.dist-info/METADATA
config_keeper2-1.1.2.dist-info/WHEEL
config_keeper2-1.1.2.dist-info/entry_points.txt
config_keeper2-1.1.2.dist-info/RECORD
