Metadata-Version: 2.1
Name: config-keeper2
Version: 1.1.2
Summary: CLI tool for keeping your personal config files in a repository
Home-page: https://github.com/Quatters/config-keeper
License: GPL-3.0-only
Author: Vladislav Korenkov
Author-email: vladnfs3@gmail.com
Requires-Python: >=3.11,<4.0
Classifier: Development Status :: 5 - Production/Stable
Classifier: Environment :: Console
Classifier: Framework :: Flake8
Classifier: Framework :: Pytest
Classifier: Intended Audience :: Developers
Classifier: Intended Audience :: End Users/Desktop
Classifier: License :: OSI Approved :: GNU General Public License v3 (GPLv3)
Classifier: Operating System :: MacOS
Classifier: Operating System :: POSIX
Classifier: Operating System :: POSIX :: Linux
Classifier: Operating System :: Unix
Classifier: Programming Language :: Python
Classifier: Programming Language :: Python :: 3
Classifier: Programming Language :: Python :: 3.11
Classifier: Programming Language :: Python :: 3 :: Only
Classifier: Typing :: Typed
Requires-Dist: pyyaml (>=6.0.1,<7.0.0)
Requires-Dist: rich (>=13.5.3,<14.0.0)
Requires-Dist: typer[all] (>=0.9.0,<0.10.0)
Project-URL: Issue Tracker, https://github.com/Quatters/config-keeper/issues
Project-URL: Repository, https://github.com/Quatters/config-keeper
